{"version":"1.0","dataSet":{"info":{"date":"20230116","occupation":"BM","channel":"MOCK","place":"ONLINE","gender":"FEMALE","ageRange":"-34","experience":"NEW"},"question":{"raw":{"text":"요즘에는 물류가 굉장히 중요해졌습니다 여러 가지 대내외적인 이슈 뿐만이 아니라 환경 변화가 잦다 보니까 물류 대란이 일어나기도 하는데요 이렇게 물류가 앞으로 나아가야 될 미래의 방향성이 뭐라고 생각하십니까","wordCount":27},"emotion":[],"intent":[]},"answer":{"raw":{"text":"저는 물류의 일원화가 일어나고 있다 라고 생각하고 있습니다. 예를 들면 쿠팡이라는 회사 같은 경우에는 직접 물류를 유통하고 또 나아가서 배송까지 이루어지는 시스템들인데요. 저는 이런 부분들이 기존과 다른 굉장히 차별점이고 또 나아가서 앞으로 우리 물류가 나아가야 될 지향점도 고객의 데이터들을 파악해서 직접 배송을 일원화하는 시스템이라고 생각합니다.","wordCount":45},"emotion":[],"intent":[{"text":"저는 이런 부분들이 기존과 다른 굉장히 차별점이고 또 나아가서 앞으로 우리 물류가 나아가야 될 지향점도 고객의 데이터들을 파악해서 직접 배송을 일원화하는 시스템이라고 생각합니다.","expression":"m_critical","category":"attitude"}],"summary":{"text":"물류의 일원화는 기존과 다른 차별점이고 물류가 나아가야 할 지향점도 고객의 데이터들을 파악해서 직접 배송을 일원화하는 시스템이라고 생각합니다.","wordCount":17}}},"rawDataInfo":{"question":{"fileFormat":"wav","fileSize":656398,"duration":20510,"samplingBit":16,"channelCount":1,"samplingRate":"16kHz","audioPath":"/Mock/01.Management/Female/New/ckmk_q_bm_f_n_320173.wav"},"answer":{"fileFormat":"wav","fileSize":1859278,"duration":58100,"samplingBit":16,"channelCount":1,"samplingRate":"16kHz","audioPath":"/Mock/01.Management/Female/New/ckmk_a_bm_f_n_320173.wav"}}}