{"version":"1.0","dataSet":{"info":{"date":"20230116","occupation":"BM","channel":"MOCK","place":"ONLINE","gender":"FEMALE","ageRange":"-34","experience":"NEW"},"question":{"raw":{"text":"시간이 촉박할 때 지원자님은 시간 관리를 어떻게 하셨습니까 지원자님의 시간 관리법이 궁금합니다","wordCount":12},"emotion":[],"intent":[]},"answer":{"raw":{"text":"시험 기간 중에 만약에 시간이 촉박한 상황이 생긴다면 저는 우선 시험 과목의 비중을 한 번 살펴볼 것 같습니다. 제가 공부를 해서 더 좋은 성적을 낼 수 있는 과목들이 있다면 그것들을 우선 앞 시간으로 배치를 해서 먼저 공부할 것 같아요. 사람들이 어찌보면 잘 못하는 걸 먼저 하는 경우가 있는데 이렇게 되면 시간이 더 많이 걸리고 공부하는 데 더 복잡해질 수 있기 때문에 부족한 시간을 더 부족하게 만드는 경우들이 있습니다. 하지만 저 같은 경우에는 제가 조금만 더 노력해서 더 좋은 결과를 낼 수 있는 과목이 있으면 그것을 먼저 공부하겠습니다. 그렇게 되면 집중도도 높아지고 빨리 공부를 마무리 할 수 있을 것 같아요. 그러면 부족한 시간이지만 시간을 더 효율적으로 사용할 수 있다고 생각이 듭니다.","wordCount":110},"emotion":[],"intent":[{"text":"","expression":"","category":"attitude"}],"summary":{"text":"시험 기간 중에 시간이 촉박한 상황이 생긴다면 제가 더 좋은 성적을 낼 수 있는 과목들을 우선 앞 시간으로 배치해서 공부할 것 같습니다. 그렇게 하면 집중도도 높아지고 빨리 공부를 마무리 할 수 있을 것 같아 시간을 더 효율적으로 사용할 수 있다고 생각합니다.","wordCount":41}}},"rawDataInfo":{"question":{"fileFormat":"wav","fileSize":300558,"duration":9390,"samplingBit":16,"channelCount":1,"samplingRate":"16kHz","audioPath":"/Mock/01.Management/Female/New/ckmk_q_bm_f_n_360886.wav"},"answer":{"fileFormat":"wav","fileSize":1838798,"duration":57460,"samplingBit":16,"channelCount":1,"samplingRate":"16kHz","audioPath":"/Mock/01.Management/Female/New/ckmk_a_bm_f_n_360886.wav"}}}