{"version":"1.0","dataSet":{"info":{"date":"20230116","occupation":"BM","channel":"MOCK","place":"ONLINE","gender":"MALE","ageRange":"55-","experience":"NEW"},"question":{"raw":{"text":"지원자님이 알고 있는 프로젝트 관리 기법이 있습니까 알고 있는 그 프로젝트 관리 기법에 대해 설명 부탁드리겠습니다 알고 계신 만큼만 말씀해 주세요","wordCount":21},"emotion":[],"intent":[]},"answer":{"raw":{"text":"프로젝트 관리라고 하면은 주로 일정 관리 그다음에 인력 관리 개발 관리 그런 것들이 해당이 될 것 같습니다. 그래서 프로젝트 관리 기법은 제가 특별히 이 부분에 대해서 전문적으로 알고 있지는 않지만 프로젝터 주요 관리 기법에는 에자엘 기법 뭐 워터폴 기법 씨피엔 기법 뭐 이런 것들이 있다 라고 제가 얘기는 들었습니다. 그래서 애자일 기법 같은 경우에는 유연성과 스피드 짧은 시간 안에 전력 질수 할 수 있다 라고 하는 거고 워터폴 기법은 연속적으로 관리하는 그런 기법을 주로 피엠들이 쓰는 그런 기법이라고 알고 있고 시피엠 이 기법은 상호 의조전전적인 활동이 요구되는 프로젝트에서 단계별 기법으로 사용하는 것으로 알고 있습니다. 그래서 저는 이 프로젝트 관리 기법에 대해서는 정확히 알 수는 없지만 아무튼 그런 것들이 있다고는 알고 있습니다.","wordCount":111},"emotion":[],"intent":[{"text":"","expression":"","category":"attitude"}],"summary":{"text":"프로젝트 관리 기법은 유연성과 스피드 짧은 시간 안에 전력 질수 할 수 있는 애자일 기법, 연속적으로 관리하는 기법을 주로 쓰는 워터폴 기법, 상호 의조전전적인 활동이 요구되는 프로젝트에서 단계별 기법으로 사용하는 시피엠 기법 등이 있습니다.","wordCount":34}}},"rawDataInfo":{"question":{"fileFormat":"wav","fileSize":459918,"duration":14370,"samplingBit":16,"channelCount":1,"samplingRate":"16kHz","audioPath":"/Mock/01.Management/Male/New/ckmk_q_bm_m_n_335334.wav"},"answer":{"fileFormat":"wav","fileSize":2714318,"duration":84820,"samplingBit":16,"channelCount":1,"samplingRate":"16kHz","audioPath":"/Mock/01.Management/Male/New/ckmk_a_bm_m_n_335334.wav"}}}