{"version":"1.0","dataSet":{"info":{"date":"20230116","occupation":"BM","channel":"MOCK","place":"ONLINE","gender":"FEMALE","ageRange":"35-44","experience":"NEW"},"question":{"raw":{"text":"어 상사가 회사의 이익에 반하는 행동을 직접 목격했다면 그때는 어떻게 하실 건가요 그리고 그렇게 하시는 이유는 무엇인가요","wordCount":17},"emotion":[],"intent":[]},"answer":{"raw":{"text":"상사가 회사의 이익에 반하는 행동을 제가 직접 목격을 하게 되었다면은 굉장히 많이 고민이 될 것 같습니다. 그런데 그 일을 너무 직접적으로 상사에게 위협을 하면서 얘기하기보다는 목격하자마자 바로 어 이거 하면 안 되지 않나요 걸리면 큰일 날 텐데요 라는 이러한 경고보다는 조금 더 약한 사실에 입각한 내용을 조금 더 전달해 줄 것 같습니다. 상사에게 이 정도만 얘기해 줘도 상사는 다 알아들을 것으로 판단이 됩니다. 만약 이렇게 사실에 반해서 얘기를 해 줬는데도 상사가 계속 회사의 이익에 반하는 행동을 한다면 저는 이 상사의 이름을 말하지는 않은 채 조금 주위 사람들을 과 주위 사람들에게 물어볼 것 같습니다. 이럴 경우 어떻게 하겠냐고 으 좀 더 고민해보고 직 간접적으로 조금 더 상사에게 그 언행이나 그 행동은 잘못되었다는 점을 조금 더 네 의견을 전달할 예정입니다.","wordCount":118},"emotion":[],"intent":[{"text":"","expression":"","category":"attitude"}],"summary":{"text":"상사가 회사의 이익에 반하는 행동을 목격하게 된다면 위협을 하기보다는 약한 사실에 입각한 내용을 전달해 줄 것 같습니다. 만약 이런 행동을 한다면 저는 상사의 이름을 말하지는 않고 주위 사람들을 과 주위 사람들에게 물어볼 것 같은데, 이럴 경우 직 간접적으로 의견을 전달할 예정입니다.","wordCount":41}}},"rawDataInfo":{"question":{"fileFormat":"wav","fileSize":499598,"duration":15610,"samplingBit":16,"channelCount":1,"samplingRate":"16kHz","audioPath":"/Mock/01.Management/Female/New/ckmk_q_bm_f_n_245141.wav"},"answer":{"fileFormat":"wav","fileSize":2750798,"duration":85960,"samplingBit":16,"channelCount":1,"samplingRate":"16kHz","audioPath":"/Mock/01.Management/Female/New/ckmk_a_bm_f_n_245141.wav"}}}