{"version":"1.0","dataSet":{"info":{"date":"20230116","occupation":"BM","channel":"MOCK","place":"ONLINE","gender":"FEMALE","ageRange":"-34","experience":"NEW"},"question":{"raw":{"text":"어 만약 질문자씨께서 최선을 다 하셨더라도 이 면접에서 최종 탈락 하실 수도 있는데요 그렇게 된다면 본인의 어떤 점이 부족해서 탈락했다고 생각을 하시겠습니까","wordCount":22},"emotion":[],"intent":[]},"answer":{"raw":{"text":"제가 생각하기에 만약 제가 이 면접에서 최종 탈락을 하게 된다면 아마 경험이 부족해서 탈락했다고 생각을 합니다. 저는 아직 나이도 많이 어리고 또 신입이기 때문에 경력이 거의 없다고 봐도 무방비 할 정도로 무방할 정도로 아직 마 아직 많이 이 분야에서 어리고 부족하다고 생각을 합니다. 물론 아직 제 또래에서는 제가 능력이 뛰어날 수도 있고 제 객관적으로 봤을 때는 잘 할 수도 잘 한다고 생각을 하지만 이게 사회에 진출했을 때는 또 다른 문제라고 생각을 합니다. 아직 제가 배워야 할 분야도 정말 많고 다른 지원자님들에 비해서 부족한 점도 많을 것이라고 생각을 합니다. 물론 제가 여기서 합격을 해서 일을 할 수 있다면 정말 너무나도 좋은 기회고 많은 것을 배울 수 있을 것이라고 생각하지만 제가 물론 탈락할 수도 있다고 생각합니다. 만약 그렇게 된다면 저는 아마 신입이고 아직 경력이 없기 때문에 탈락하지 않을까 라는 생각을 합니다. 이러한 부분은 앞으로 제가 차차 이 분야에서 경력을 쌓고 또 새로운 일들을 많이 해보면은 이러한 부분은 충분히 보완될 것이라고 생각을 합니다. 그렇기에 앞으로 정말 최선을 다할 자신이 있으니 이 면접에서 꼭 붙고 싶다는 말씀을 드리고 싶습니다.","wordCount":165},"emotion":[],"intent":[{"text":"","expression":"","category":"attitude"}],"summary":{"text":"이 면접에서 최종 탈락하게 된다면 아마 경험이 부족해서 탈락했다고 생각하며, 배워야 할 분야도 많고 다른 지원자님들에 비해서 부족한 점도 많을 것이라고 생각합니다. 만약 그렇게 된다면 아마 신입이고 아직 경력이 없기 때문에 탈락하지 않을까 라는 생각을 합니다.","wordCount":36}}},"rawDataInfo":{"question":{"fileFormat":"wav","fileSize":425678,"duration":13300,"samplingBit":16,"channelCount":1,"samplingRate":"16kHz","audioPath":"/Mock/01.Management/Female/New/ckmk_q_bm_f_n_225917.wav"},"answer":{"fileFormat":"wav","fileSize":2584398,"duration":80760,"samplingBit":16,"channelCount":1,"samplingRate":"16kHz","audioPath":"/Mock/01.Management/Female/New/ckmk_a_bm_f_n_225917.wav"}}}