{"version":"1.0","dataSet":{"info":{"date":"20230116","occupation":"BM","channel":"MOCK","place":"ONLINE","gender":"MALE","ageRange":"35-44","experience":"NEW"},"question":{"raw":{"text":"만약 이 면접에서 최종 탈락하게 되신다면 어떤 점이 부족해서 탈락했다고 생각을 하실지 어 설명해 주시기를 바랍니다","wordCount":16},"emotion":[],"intent":[]},"answer":{"raw":{"text":"제가 이 최종 면접에서 탈락하게 된다면 제가 이 분야에 대한 전문 지식이 부족하다고 여러분들께서 판단하셨기 때문이라고 생각합니다. 저는 이 분야와는 동떨어진 분야에서 오랜 시간을 일해 온 사람입니다. 그래서 제가 이 분야의 일을 했을 때 기존의 다른 분야의 지식과 새로운 시각을 제공해 줄 수 있다고 생각합니다. 하지만 손바닥도 마주쳐야 소리가 나듯이 제가 준비되었다고 생각하더라도 이 최종 면접에서 탈락이 된다면 아직 부족한 면이 많다는 것을 알려주시는 기회라고 생각을 하고 더 이 분야에 대한 지식을 습득하는 데 노력할 것입니다.","wordCount":76},"emotion":[],"intent":[{"text":"","expression":"","category":"attitude"}],"summary":{"text":"최종 면접에서 탈락하게 된다면 아직 부족한 면이 많다는 것을 알려주시는 기회라고 생각하며 더 이 분야에 대한 지식을 습득하는 데 노력할 것입니다.","wordCount":21}}},"rawDataInfo":{"question":{"fileFormat":"wav","fileSize":505678,"duration":15800,"samplingBit":16,"channelCount":1,"samplingRate":"16kHz","audioPath":"/Mock/01.Management/Male/New/ckmk_q_bm_m_n_345542.wav"},"answer":{"fileFormat":"wav","fileSize":2049678,"duration":64050,"samplingBit":16,"channelCount":1,"samplingRate":"16kHz","audioPath":"/Mock/01.Management/Male/New/ckmk_a_bm_m_n_345542.wav"}}}