{"version":"1.0","dataSet":{"info":{"date":"20230116","occupation":"BM","channel":"MOCK","place":"ONLINE","gender":"FEMALE","ageRange":"-34","experience":"NEW"},"question":{"raw":{"text":"동물 실험이 인간에게 주는 이익에 관해서 말해주세요 동물 실험에 대한 지원자 분의 생각도 말해주세요","wordCount":14},"emotion":[],"intent":[]},"answer":{"raw":{"text":"일단 제가 동물 실험에 대해서 가지고 있는 생각은 조금 양가적인 감정이라고 말씀드릴 수 있겠습니다. 기본적으로 동물 실험을 하면 안 된다는 생각을 가지고는 있는데요. 그것이 중요한 이유 중 하나는 동물의 생명 역시 인간의 생명 그리고 어 그런 비 기타 비슷한 것들 존엄성이라든지 어떤 동물이 가진 권리가 인간과 굉장히 동등하게 여겨지지는 않는다고 하더라도 비슷한 범위 내에서 존중되어야 한다는 생각이 제 머릿속에 깔려있는 것 같습니다. 그래서 어 동물 실험이 주는 이익이 있음에도 불구하고 저는 일단 기본적으로는 조금 더 방어적인 자세로 동물 실험을 하지 않았으면 좋겠다 왜냐하면 그들 역시 쾌고를 가진 어떤 생명체이고 그들에게 많은 것을 얻을 수 있다 라고 하더라도 그것이 어떤 그들의 존엄성이나 권리를 굉장히 해치는 일일 수 있기 때문에 부정적인 생각을 가지고 있습니다. 그렇지만 동물 실험이라는 것이 주는 이익도 굉장히 분명하다고 생각하는 바인데요. 인간이 먼저 체험하고 인간의 존엄성을 반드시 해칠 수 밖에 없다고 생각되는 어떤 면모들이 있을 때 그런 것들을 어떻게 해결해 나갈 수 있을지 그리고 어떻게 좀 잘 인간에게 바로 적용하지 않고 그 전에 적용했을 때 장점이 있을 지에 대해서 그 확인할 수 있다는 부분에 있어서는 동물 실험이 확실히 인간에게 주는 이익이 명확하다고 생각하고 있습니다.","wordCount":175},"emotion":[],"intent":[{"text":"","expression":"","category":"attitude"}],"summary":{"text":"동물이 인간의 존엄성을 해칠 수 밖에 없다고 생각되는 부분들을 인간에게 바로 적용하지 않고 그 전에 적용했을 때 장점이 있을 지에 대해서 확인할 수 있다는 부분에 있어서는 동물 실험이 확실히 인간에게 주는 이익이 명확하다고 생각하고 있습니다.","wordCount":35}}},"rawDataInfo":{"question":{"fileFormat":"wav","fileSize":252878,"duration":7900,"samplingBit":16,"channelCount":1,"samplingRate":"16kHz","audioPath":"/Mock/01.Management/Female/New/ckmk_q_bm_f_n_387045.wav"},"answer":{"fileFormat":"wav","fileSize":3753678,"duration":117300,"samplingBit":16,"channelCount":1,"samplingRate":"16kHz","audioPath":"/Mock/01.Management/Female/New/ckmk_a_bm_f_n_387045.wav"}}}