{"version":"1.0","dataSet":{"info":{"date":"20230116","occupation":"BM","channel":"MOCK","place":"ONLINE","gender":"MALE","ageRange":"35-44","experience":"NEW"},"question":{"raw":{"text":"몇 년 전 우버 택시와 관련된 논란이 있었다는 것을 알고 계십니까 지원자님께서는 이 문제에 대해서 어떻게 생각을 하십니까","wordCount":18},"emotion":[],"intent":[]},"answer":{"raw":{"text":"저는 처음부터 우버택시 도입에 찬성하는 입장이었습니다. 해외에서 살아본 경험이 많기 때문에 우버택시의 장점을 잘 알고 있었습니다. 하지만 당시에 택시 업계가 고사될 수 있다는 섣부른 주장 때문에 그 우버택시 도입이 안 된 것이 굉장히 불만스러웠습니다. 몇 년이 지난 지금 상황을 보면은 더욱 안 좋아진 것 같습니다. 택시 업계는 몇몇 회사에 너무 종속되었고 또 벌 수 있는 수당이 점점 적어지고 본인들의 업무량도 많아지다 보니 많은 택시 기사들이 택시 업계에서 이탈하여 배달로 가고 있다는 실정을 들었습니다. 그럴 것이라면 우버택시를 도입하여 차라리 자연스럽게 택시 업계에 집중되어 있던 운송수단 능력이 분산될 수 있도록 해야 됐던 것이 아닌가 라고 지금도 생각하고 있습니다.","wordCount":96},"emotion":[],"intent":[{"text":"","expression":"","category":"attitude"}],"summary":{"text":"저는 처음부터 우버택시 도입에 찬성했습니다. 우버택시의 장점을 잘 알고 있었지만 택시 업계가 고사될 수 있다는 섣부른 주장 때문에 도입이 안 된 것이 불만스러웠습니다. 차라리 우버택시를 도입하여 운송수단 능력이 분산되도록 해야 되지 않았나 생각합니다.","wordCount":33}}},"rawDataInfo":{"question":{"fileFormat":"wav","fileSize":427598,"duration":13360,"samplingBit":16,"channelCount":1,"samplingRate":"16kHz","audioPath":"/Mock/01.Management/Male/New/ckmk_q_bm_m_n_354439.wav"},"answer":{"fileFormat":"wav","fileSize":2576718,"duration":80520,"samplingBit":16,"channelCount":1,"samplingRate":"16kHz","audioPath":"/Mock/01.Management/Male/New/ckmk_a_bm_m_n_354439.wav"}}}