{"version":"1.0","dataSet":{"info":{"date":"20230116","occupation":"BM","channel":"MOCK","place":"ONLINE","gender":"FEMALE","ageRange":"-34","experience":"NEW"},"question":{"raw":{"text":"지원자님께서는 직장을 선택할 때 가장 중요하게 생각하는 세 가지가 무엇인가요 그 세 가지를 각각 구체적으로 제시해 주시기 바랍니다","wordCount":18},"emotion":[],"intent":[]},"answer":{"raw":{"text":"아 네 저는 어 회사에 회사 회사를 선택하는 기준은 제가 속한 회사가 지속 성장이 가능하고 어 그 최선을 다하는 노력을 통해서 제 자신과 함께 발전해 나갈 수 있는지를 좀 중요하게 생각하고요. 어 다음에는 어떤 비전입니다. 그래서 제가 선호하는 분야에서 경쟁력을 충분히 갖추고 있어서 이 기업에서 함께 발전하면서 어떤 그 향후에 그 성장 가능성이 있는지를 확인하는 편이고요. 어 그리고 저는 또 경영 방침 인재상도 저 제가 그 인재상에 맞아 떨어지는지가 또 중요하다고 생각을 합니다. 어 만약에 무조건 이렇게 무조건 그 회사의 인재상이 뭐 창의적인 사람 뭐 이렇게만 만약에 어 추구를 하신다면 어 저는 창의성보다는 당연히 창의성도 있지만 협업하고 어 고객을 꾸준하게 생각하는 그런 마음이 또 있기 때문에 인재상이 또 맞지 않는다면 저와 회사가 또 맞지 않다고 생각을 해서 인재상도 중요하게 보는 편입니다.","wordCount":121},"emotion":[],"intent":[{"text":"","expression":"","category":"attitude"}],"summary":{"text":"회사를 선택하는 기준은 제가 속한 회사가 지속 성장이 가능하고 제 자신과 함께 발전해 나갈 수 있는지를 중요하게 생각하며, 앞으로 성장 가능성이 있는지 확인하는 편입니다. 또 경영 방침 인재상도 제가 그 인재상에 맞아떨어지는지가 중요하다고 생각을 합니다.","wordCount":35}}},"rawDataInfo":{"question":{"fileFormat":"wav","fileSize":659278,"duration":20600,"samplingBit":16,"channelCount":1,"samplingRate":"16kHz","audioPath":"/Mock/01.Management/Female/New/ckmk_q_bm_f_n_315219.wav"},"answer":{"fileFormat":"wav","fileSize":2560078,"duration":80000,"samplingBit":16,"channelCount":1,"samplingRate":"16kHz","audioPath":"/Mock/01.Management/Female/New/ckmk_a_bm_f_n_315219.wav"}}}