{"version":"1.0","dataSet":{"info":{"date":"20230116","occupation":"BM","channel":"MOCK","place":"ONLINE","gender":"MALE","ageRange":"55-","experience":"NEW"},"question":{"raw":{"text":"면접자님께서 본인이 현재 가지고 있는 위치보다 더 어려운 목표를 달성해 본 경험이 있다면 그 경험에 대해서 얘기해 주시겠어요","wordCount":18},"emotion":[],"intent":[]},"answer":{"raw":{"text":"현재 위치보다 어려운 목표를 달성한 적이 있느냐 물으신다면은 저는 전에 직장에서 제가 계획한 북 러닝 프로젝트를 말씀드리고 싶습니다. 에 가산에 교육 업체에 근무하던 중 북 러닝을 기획하여 위에 올렸는데 제가 졸지에 팀장을 맡아 그 일을 진행하게 되었습니다. 고용 보험에 가입한 직장인을 위한 교육 과정을 만드는 것인데 매일 교보문고와 도서관에서 책들을 뒤적이고 대상 책자를 선정한 다음에는 각 출판사에 연락하여 저작권 사용 승인을 받고 저자와 전문 필자를 찾아 교육 내용의 저술을 부탁하고 대학원의 박사 과정 학생들을 섭외하여 조교 요원으로 위촉하는 등 일련의 과정들은 우리 모든 팀원들이 힘을 합한 열정 때문이었습니다. 그렇게 만들어진 교육 과정들이 좋은 평가를 받으며 여러 업체에서 호응을 받은 것은 지금 생각해도 가슴 뛰는 일이었습니다.","wordCount":105},"emotion":[{"text":"그렇게 만들어진 교육 과정들이 좋은 평가를 받으며 여러 업체에서 호응을 받은 것은 지금 생각해도 가슴 뛰는 일이었습니다.","expression":"p-achievement","category":"positive"}],"intent":[{"text":"","expression":"","category":"attitude"}],"summary":{"text":"저는 직장에서 북 러닝 프로젝트를 했습니다. 고용 보험에 가입한 직장인을 위한 교육 과정을 만드는 것이었는데, 모든 팀원들이 힘을 합쳤기 때문입니다. 이렇게 만들어진 교육 과정들이 좋은 평가를 받고 여러 업체에서 호응을 받은 것은 가슴 뛰었습니다.","wordCount":34}}},"rawDataInfo":{"question":{"fileFormat":"wav","fileSize":317518,"duration":9920,"samplingBit":16,"channelCount":1,"samplingRate":"16kHz","audioPath":"/Mock/01.Management/Male/New/ckmk_q_bm_m_n_352747.wav"},"answer":{"fileFormat":"wav","fileSize":2615438,"duration":81730,"samplingBit":16,"channelCount":1,"samplingRate":"16kHz","audioPath":"/Mock/01.Management/Male/New/ckmk_a_bm_m_n_352747.wav"}}}