{"version":"1.0","dataSet":{"info":{"date":"20230116","occupation":"BM","channel":"MOCK","place":"ONLINE","gender":"FEMALE","ageRange":"-34","experience":"NEW"},"question":{"raw":{"text":"지원자님의 단점과 장점을 본인이 생각하는 것이 아닌 주변 사람들이 생각하는 관점에서 말씀해 보시기 바랍니다","wordCount":14},"emotion":[],"intent":[]},"answer":{"raw":{"text":"다른 주변인들이 생각하는 저의 단점은 표정 변화를 잘 알 수가 없다 라는 거였는데요. 그래서 간혹 이제 어떤 친구는 나는 니가 무슨 생각을 하는지 모르겠다 라고 이야기를 한 적도 있었습니다. 그래서 저는 이것을 고치기 위해서 거울을 보면서 표정 연습을 많이 했습니다. 나는 나대로 웃는 거라고 하지만 이게 살짝 이렇게 살짝 입꼬리가 올라가는 거를 다른 사람들은 잘 못 볼 수가 있으니까요. 그래서 활짝 웃는 법과 약간 표정의 변화를 크게 크게 하는 연습을 했었고요. 그리고 이 단점을 저는 장점으로 승화를 시켰습니다. 저는 표정 변화가 그렇게 크지 않다 라는 거는 어떻게 보면은 감정에 크게 영향을 받지 않는다 라고 말씀을 드릴 수도 있을 것 같은데요. 그래서 어찌 보면 그렇게 사람을 상대하는 그런 자리에서는 굉장히 유리하게 적용을 했습니다. 사실상 만약에 큰 프로젝트를 맡고 있다 발표를 해야 된다 굉장히 두렵고 떨리지만 표정 변화는 굉장히 평온하게 그런 침착한 모습을 유지해서 굉장히 항상 긍정적인 평가를 받았었고요. 네 이것은 저의 단점을 장점으로 잘 승화 시켰다 라고 말씀을 드릴 수 있을 것 같습니다.","wordCount":152},"emotion":[],"intent":[{"text":"","expression":"","category":"attitude"}],"summary":{"text":"주변인들은 표정 변화를 잘 알 수 없다는 단점을 가지고 있는데, 이것을 고치기 위해 표정 연습을 많이 했습니다. 그리고 표정 변화가 크지 않다는 단점은 감정에 크게 영향을 받지 않는다는 장점으로 승화시켰고, 발표를 하는 자리에 유리하게 적용했습니다.","wordCount":35}}},"rawDataInfo":{"question":{"fileFormat":"wav","fileSize":424398,"duration":13260,"samplingBit":16,"channelCount":1,"samplingRate":"16kHz","audioPath":"/Mock/01.Management/Female/New/ckmk_q_bm_f_n_212980.wav"},"answer":{"fileFormat":"wav","fileSize":2359758,"duration":73740,"samplingBit":16,"channelCount":1,"samplingRate":"16kHz","audioPath":"/Mock/01.Management/Female/New/ckmk_a_bm_f_n_212980.wav"}}}