{"version":"1.0","dataSet":{"info":{"date":"20230116","occupation":"BM","channel":"MOCK","place":"ONLINE","gender":"MALE","ageRange":"55-","experience":"NEW"},"question":{"raw":{"text":"일을 하면서 어려울 것으로 예상되는 점은 무엇인가요 그리고 그것을 어떻게 대처해 나가실 것인가요","wordCount":13},"emotion":[],"intent":[]},"answer":{"raw":{"text":"인간관계입니다. 모든 일은 사람이 합니다. 나 혼자 하는 일 같아도 사실은 많은 사람들과 당연히 연결되어 있을 수밖에 없을 것입니다. 어느 순간 순간 혼자 일을 할진 몰라도 그 일은 어떤 다른 사람과 과의 연관 관계를 통해서 융합 발전되어 어떠한 완성품으로 나타날 것입니다. 그 과정에 부딪치는 것이 서로 조직원 간에 이해 득실입니다. 사소한 문제 또는 큰 문제 모두 계속적으로 서로 대화하고 인견을 나누면서 어떤 조직의 목적물은 만들어지는 것입니다. 그때 매우 독특한 사람이거나 나와 도저히 맞지 않는 성향의 사람과 장시간 맞닥뜨려야 되는 일이 생긴다면 그것이 가장 어려운 일일 거라고 봅니다. 그때 무조건 방법은 역지사지입니다. 상대방의 입장에서 생각하고 그 사람을 이해하려는 노력을 하면 그 어려움은 많이 줄어들 것입니다. 또한 내가 어떻게 그 사람을 설득할 거 설득할 것인지 내가 그에게 가깝게 장시간 친밀하게 접근하는 것입니다. 그와의 어떤 상대와의 동질성을 만들어내야 일은 쉽게 해결이 됩니다.","wordCount":129},"emotion":[],"intent":[{"text":"","expression":"","category":"attitude"}],"summary":{"text":"모든 일은 사람이 하며 그 일은 다른 사람과의 연관 관계를 통해 융합 발전되어 완성품으로 나타날 것입니다. 그 과정에서 서로 대화하고 의견 나누며 어떤 조직의 목적물은 만들어집니다. 그 때 상대방의 입장에서 생각하고 이해하려는 노력을 하면 어려움은 줄어들 것이며 장시간 친밀하게 접근하는 것입니다.","wordCount":41}}},"rawDataInfo":{"question":{"fileFormat":"wav","fileSize":326798,"duration":10210,"samplingBit":16,"channelCount":1,"samplingRate":"16kHz","audioPath":"/Mock/01.Management/Male/New/ckmk_q_bm_m_n_357477.wav"},"answer":{"fileFormat":"wav","fileSize":3471438,"duration":108480,"samplingBit":16,"channelCount":1,"samplingRate":"16kHz","audioPath":"/Mock/01.Management/Male/New/ckmk_a_bm_m_n_357477.wav"}}}