{"version":"1.0","dataSet":{"info":{"date":"20230116","occupation":"BM","channel":"MOCK","place":"ONLINE","gender":"FEMALE","ageRange":"-34","experience":"NEW"},"question":{"raw":{"text":"지원자님께서는 특별히 가고 싶은 회사가 있으신가요 있다면 특정 도메인이 중요한지 회사 분위기가 중요한지 어떤 것을 중요하게 보시는지 궁금합니다","wordCount":18},"emotion":[],"intent":[]},"answer":{"raw":{"text":"어 저는 특정 도메인보다는 회사의 분위기가 중요하다고 생각을 합니다. 어 가장 중요한 것은 아무래도 이제 같이 일하는 동료들이라고 생각을 하는데요. 그 동료들이 모였을 때 분위기가 어 좋아야 일할 맛도 생기고 그리고 의견을 좀 자유롭게 적극적으로 내세울 수 있는 그런 환경이 될 수 있다고 생각을 합니다. 어 그래서 회사의 분위기가 어떤 뭐 창의적인 결과를 내거나 할 때 가장 중요하다고 생각을 합니다.","wordCount":60},"emotion":[],"intent":[{"text":"","expression":"","category":"attitude"}],"summary":{"text":"창의적인 결과를 내거나 할 때 회사 분위기가 가장 중요하다고 생각하며, 같이 일하는 동료들이 모였을 때 가장 중요한 것은 회사의 분위기라고 생각합니다.","wordCount":21}}},"rawDataInfo":{"question":{"fileFormat":"wav","fileSize":467918,"duration":14620,"samplingBit":16,"channelCount":1,"samplingRate":"16kHz","audioPath":"/Mock/01.Management/Female/New/ckmk_q_bm_f_n_416293.wav"},"answer":{"fileFormat":"wav","fileSize":1205838,"duration":37680,"samplingBit":16,"channelCount":1,"samplingRate":"16kHz","audioPath":"/Mock/01.Management/Female/New/ckmk_a_bm_f_n_416293.wav"}}}