{"version":"1.0","dataSet":{"info":{"date":"20230116","occupation":"BM","channel":"MOCK","place":"ONLINE","gender":"FEMALE","ageRange":"-34","experience":"NEW"},"question":{"raw":{"text":"사내 스터디를 만들어서 공부를 할 수 있다면 어떤 것을 공부하고 싶으신가요 이유도 함께 제시해 주시기 바랍니다","wordCount":16},"emotion":[],"intent":[]},"answer":{"raw":{"text":"영어 스터디를 만들고 싶습니다. 요즘은 영어가 기본인 세대가 되었고 더 나아가 영어 플러스 다른 언어를 할 수 있는지를 보는 시대가 되었습니다. 하지만 학창 싱얼 시절 영어가 항상 부족하다고 느꼈지만 그만큼의 노력은 하지 않았습니다. 영어를 못한다고 삶을 못 살지는 않지만 해외 여행을 좋아하는 사람으로서 더 넓은 나라들로 여행을 떠나고 싶습니다. 그때 필요한 것은 언어라고 생각합니다. 그렇기 때문에 저는 만든다면은 영어 스터디로 만들고 싶습니다.","wordCount":62},"emotion":[],"intent":[{"text":"","expression":"","category":"attitude"}],"summary":{"text":"요즘은 영어가 기본인 세대가 되었고 더 나아가 영어 플러스 다른 언어를 할 수 있는지를 보는 시대가 되었습니다. 영어가 아닌 더 넓은 나라들로 여행을 떠나고 싶습니다.","wordCount":25}}},"rawDataInfo":{"question":{"fileFormat":"wav","fileSize":409678,"duration":12800,"samplingBit":16,"channelCount":1,"samplingRate":"16kHz","audioPath":"/Mock/01.Management/Female/New/ckmk_q_bm_f_n_342616.wav"},"answer":{"fileFormat":"wav","fileSize":1325518,"duration":41420,"samplingBit":16,"channelCount":1,"samplingRate":"16kHz","audioPath":"/Mock/01.Management/Female/New/ckmk_a_bm_f_n_342616.wav"}}}