{"version":"1.0","dataSet":{"info":{"date":"20230116","occupation":"BM","channel":"MOCK","place":"ONLINE","gender":"MALE","ageRange":"-34","experience":"NEW"},"question":{"raw":{"text":"지원자분의 상사 분께서 본인의 업무와는 무관한 일을 시키신다고 하더라도 잘 수행해 낼 자신이 있으신지 궁금합니다 혹은 수행하시지 않을 것인지 답변해 주세요","wordCount":21},"emotion":[],"intent":[]},"answer":{"raw":{"text":"상사가 업무에 무관한 일을 시킨다 하더라도 어떠한 업무이냐 에 따라 저의 선택이 많이 달라질 것 같습니다. 만약 그 업무가 정말 상사의 개인적인 일인지 아니면 조금이라도 회사와 그리고 나의 업무와 관련이 있는 것인지 를 조금 생각해 볼 것 같습니다. 그리고 현재 저에게 주어진 일이 어느 정도의 상황인지도 파악해 보는 것이 중요하다고 생각합니다. 내가 지금 급하게 또는 중요하게 해야 할 일이 많은 상황 가운데에 있음에도 불구하고 상사가 어떠한 일을 시켰다고 해서 그것을 하는 것은 마땅치 않다고 생각합니다. 그것은 저에게 있어서 제가 어 해야 할 바를 하지 않고 하는 거기 때문에 직무 유기와도 같은 일이기 때문입니다. 그렇기 때문에 적어도 어 상사가 시킨 그 무관한 일이 회사와 관련된 일이거나 저의 업무와 조금이라도 관련된 일이라면 일단 저의 앞에 주어진 일들에 대한 부분을 생각을 해 보고 만약 내가 할 수 있는 부분이라고 생각이 든다면 그 일들을 처리해 나갈 것 같습니다. 하지만 이와 반대로 만약 상사의 개인적인 그러한 일이라고 한다면 저는 제가 할 수 있는 일이라 하더라도 아마 다른 핑계를 대어서 다른 일이 아직 있다 는 핑계 등등 어 상사의 기분을 상하지 않을 정도의 그러한 답변들을 구해서 그 일들을 하지 않을 것 같습니다.","wordCount":176},"emotion":[],"intent":[{"text":"","expression":"","category":"attitude"}],"summary":{"text":"상사가 업무와 무관한 일을 시킨다 하더라도 그 업무가 정말 상사의 개인적인 것인지, 조금이라도 회사와 저의 업무와 관련이 있는 것인지를 생각해 볼 것 같습니다. 그리고 현재 제가 해야 할 일이 많은 상황 가운데에 있음에도 불구하고 상사가 어떠한 일을 시켰다고 해서 그것을 하는 것은 마땅하지 않다고 생각합니다.","wordCount":45}}},"rawDataInfo":{"question":{"fileFormat":"wav","fileSize":452558,"duration":14140,"samplingBit":16,"channelCount":1,"samplingRate":"16kHz","audioPath":"/Mock/01.Management/Male/New/ckmk_q_bm_m_n_349046.wav"},"answer":{"fileFormat":"wav","fileSize":3274958,"duration":102340,"samplingBit":16,"channelCount":1,"samplingRate":"16kHz","audioPath":"/Mock/01.Management/Male/New/ckmk_a_bm_m_n_349046.wav"}}}