{"version":"1.0","dataSet":{"info":{"date":"20230116","occupation":"BM","channel":"MOCK","place":"ONLINE","gender":"FEMALE","ageRange":"-34","experience":"NEW"},"question":{"raw":{"text":"무언가를 달성하기 위해서 목표를 세우고 이 삼 년 동안 열심히 노력해서 그 목표를 달성한 경험이 있다면 소개해 주세요","wordCount":18},"emotion":[],"intent":[]},"answer":{"raw":{"text":"저는 무언가를 달성하기 위해 목표를 세우고 노력을 해서 목표를 달성한 경험이 있습니다. 저는 목표 관리를 어떻게 관리해야 하는지에 대한 방법은 구체적으로 알지 못합니다. 하지만 목표 관리에 대한 중요성은 알고 있습니다. 규모가 작은 소규모 기업이나 중소기업들은 목표 관리에 힘을 써야 효과를 얻어낼 수 있다고 생각합니다. 저는 이것을 노력을 하면서 목표에 달성한 경험이 있습니다.","wordCount":52},"emotion":[],"intent":[{"text":"","expression":"","category":"attitude"}],"summary":{"text":"소규모 기업이나 중소기업들은 목표 관리에 힘을 써야 효과를 얻어낼 수 있다고 생각합니다. 저는 이것을 노력을 하면서 목표에 달성한 경험이 있습니다.","wordCount":20}}},"rawDataInfo":{"question":{"fileFormat":"wav","fileSize":612558,"duration":19140,"samplingBit":16,"channelCount":1,"samplingRate":"16kHz","audioPath":"/Mock/01.Management/Female/New/ckmk_q_bm_f_n_317713.wav"},"answer":{"fileFormat":"wav","fileSize":1380558,"duration":43140,"samplingBit":16,"channelCount":1,"samplingRate":"16kHz","audioPath":"/Mock/01.Management/Female/New/ckmk_a_bm_f_n_317713.wav"}}}