{"version":"1.0","dataSet":{"info":{"date":"20230116","occupation":"BM","channel":"MOCK","place":"ONLINE","gender":"FEMALE","ageRange":"55-","experience":"NEW"},"question":{"raw":{"text":"어 혹시 지원자님께서는 매일매일 공부하고 있는 분야가 있으신가요 있으시다면 어 그 분야를 공부하고 계신 이유는 무엇인지 함께 설명해 주시기를 바랍니다","wordCount":20},"emotion":[],"intent":[]},"answer":{"raw":{"text":"혹시 매일 공부하고 있는 분야가 따로 있나요. 있다면 그걸 왜 공부하는지도 함께 설명해 주세요. 이 질문에 대한 저의 답변을 말씀드리겠습니다. 저는 시간이 날 때마다 소방 기술 자격증 취득을 위해 공부를 준비하고 있습니다. 소방 관련 업종은 우리의 생명과 안전 안전이 직접 연관이 있기 때문에 어릴 때부터 관심이 많았던 분야였습니다. 소방 관련 기술 자격증은 공부하기는 어렵지만 자격증을 가지고 있으면 희소성이 있어 취업도 유리하고 노후에도 계속 일할 수 있을 거라 생각되어져서 노후에 할 일에 대비하여 배우고 있습니다. 지금까지는 생명의 소중함과 화재 방지에 관련된 것까지 배워 왔습니다. 요즘 무엇을 공부하는지에 대한 저의 답변을 말씀드렸습니다. 감사합니다.","wordCount":91},"emotion":[{"text":"소방 관련 업종은 우리의 생명과 안전 안전이 직접 연관이 있기 때문에 어릴 때부터 관심이 많았던 분야였습니다.","expression":"p-interest","category":"positive"}],"intent":[{"text":"소방 관련 기술 자격증은 공부하기는 어렵지만 자격증을 가지고 있으면 희소성이 있어 취업도 유리하고 노후에도 계속 일할 수 있을 거라 생각되어져서 노후에 할 일에 대비하여 배우고 있습니다.","expression":"c_imp","category":"personality"}],"summary":{"text":"저는 시간이 날 때마다 소방 기술 자격증 취득을 위해 공부하고 있습니다. 소방 업종은 생명과 안전 안전이 직접 연관이 있어서 어릴 때부터 관심이 많았던 분야입니다. 소방 관련 기술 자격증은 희소성이 있어 노후에 할 일에 대비하여 배우고 싶습니다.","wordCount":36}}},"rawDataInfo":{"question":{"fileFormat":"wav","fileSize":460878,"duration":14400,"samplingBit":16,"channelCount":1,"samplingRate":"16kHz","audioPath":"/Mock/01.Management/Female/New/ckmk_q_bm_f_n_211823.wav"},"answer":{"fileFormat":"wav","fileSize":2428238,"duration":75880,"samplingBit":16,"channelCount":1,"samplingRate":"16kHz","audioPath":"/Mock/01.Management/Female/New/ckmk_a_bm_f_n_211823.wav"}}}