{"version":"1.0","dataSet":{"info":{"date":"20230116","occupation":"BM","channel":"MOCK","place":"ONLINE","gender":"MALE","ageRange":"35-44","experience":"NEW"},"question":{"raw":{"text":"만약 우리 회사가 해외 무대로 진출을 하게 된다면 어디로 진출하는 게 좋을 것 같은지 그 이유와 함께 답변해 주시기 바랍니다","wordCount":20},"emotion":[],"intent":[]},"answer":{"raw":{"text":"저는 우리 회사가 새로운 해외 무대로 삼아야 할 곳은 구 동구권의 유럽권 국가들이라고 생각합니다. 지금 현재 러시아와 우쿠라이나의 전쟁으로 인해 전 세계적인 경제 불황이 찾아올 것인데요. 전쟁이란 것은 언젠가 끝나게 될 것이며 가장 피해가 많은 곳에 가장 많은 자원의 집중이 이루어 질 것이기 때문에 지금 현재는 앞이 보이지 않는 상황이라 할지라도 앞으로 변화하게 될 세계 정세에 대비하기 위해서라도 저는 우리 회사가 앞으로 주 해외 무대에 타겟을 구 동구권 유럽 국가들로 해야 한다고 생각합니다.","wordCount":73},"emotion":[],"intent":[{"text":"전쟁이란 것은 언젠가 끝나게 될 것이며 가장 피해가 많은 곳에 가장 많은 자원의 집중이 이루어 질 것이기 때문에 지금 현재는 앞이 보이지 않는 상황이라 할지라도 앞으로 변화하게 될 세계 정세에 대비하기 위해서라도 저는 우리 회사가 앞으로 주 해외 무대에 타겟을 구 동구권 유럽 국가들로 해야 한다고 생각합니다.","expression":"m_holistic","category":"attitude"}],"summary":{"text":"러시아와 우쿠라이나의 전쟁으로 인한 세계적인 경제 불황이 찾아올 것이라고 할 때, 변화하게 될 세계 정세에 대비하기 위해서라도 우리 회사는 구 동구권의 유럽권 국가들로 주 해외 무대로 삼아야 합니다.","wordCount":28}}},"rawDataInfo":{"question":{"fileFormat":"wav","fileSize":339278,"duration":10600,"samplingBit":16,"channelCount":1,"samplingRate":"16kHz","audioPath":"/Mock/01.Management/Male/New/ckmk_q_bm_m_n_339019.wav"},"answer":{"fileFormat":"wav","fileSize":2183118,"duration":68220,"samplingBit":16,"channelCount":1,"samplingRate":"16kHz","audioPath":"/Mock/01.Management/Male/New/ckmk_a_bm_m_n_339019.wav"}}}