{"version":"1.0","dataSet":{"info":{"date":"20230116","occupation":"BM","channel":"MOCK","place":"ONLINE","gender":"MALE","ageRange":"35-44","experience":"NEW"},"question":{"raw":{"text":"지원자님의 장점과 단점을 설명해 주시고 그것을 특화시키거나 극복하기 위해 기울였던 노력도 같이 얘기해 주세요","wordCount":14},"emotion":[],"intent":[]},"answer":{"raw":{"text":"저의 장점은 문제 해결력입니다. 저는 하나의 상황이 주어졌을 때 정말 다각도로 바라볼 수 있고 편견을 가지지 않고 여러 방향으로 문제를 해결할 수 있는 방법들을 찾아내는 그런 트러블 슈터 라고 많이 지인들이 말씀을 해 주셨습니다. 이는 항상 제가 와이라는 개념으로 왜 이런 일이 생겼을까 부터 시작해서 어떻게 하면은 더 창의적이고 효과적인 해결 방법을 찾을 수 있을까 라는 고민까지 굉장히 몰입하면서 생각하기 때문에 문제 해결력이 키워졌는데요. 때문에 이 문제 해결을 더 극화시키기 위해서 저는 더 많은 이슈들을 검색하고 결과들 그 케이스들을 분석하고 그리고 학습하고 있습니다. 또한 다른 인 그 다른 유명한 명사분들께서 하는 의사 결정이나 판단들도 많이 참고하고 있구요. 단점은 글로벌 역량이 쪼금 부족하다고 생각합니다. 제가 몸 담을 아이티 조직은 굉장히 해외 영어들도 많은데 이 부분에 있어서 조금 더 지식을 쌓고 조직에 도움될 수 있도록 스터디하도록 하겠습니다.","wordCount":125},"emotion":[],"intent":[{"text":"","expression":"","category":"attitude"}],"summary":{"text":"저는 다각도로 바라볼 수 있고 편견없이 여러방향으로 문제를 해결하는 트러블 슈터 입니다. 문제 해결을 위해 더 많은 이슈들을 검색하고 결과들을 분석하고 학습하고 있습니다. 단점은 글로벌 역량이 조금 부족하다고 생각합니다.","wordCount":29}}},"rawDataInfo":{"question":{"fileFormat":"wav","fileSize":390158,"duration":12190,"samplingBit":16,"channelCount":1,"samplingRate":"16kHz","audioPath":"/Mock/01.Management/Male/New/ckmk_q_bm_m_n_421049.wav"},"answer":{"fileFormat":"wav","fileSize":2655438,"duration":82980,"samplingBit":16,"channelCount":1,"samplingRate":"16kHz","audioPath":"/Mock/01.Management/Male/New/ckmk_a_bm_m_n_421049.wav"}}}