{"version":"1.0","dataSet":{"info":{"date":"20230116","occupation":"BM","channel":"MOCK","place":"ONLINE","gender":"FEMALE","ageRange":"55-","experience":"NEW"},"question":{"raw":{"text":"배달의민족을 사용하시면서 서비스에서 아쉬웠던 부분이 있었나요 있었다면 그 점에 대해서 구체적으로 말씀해 주실 수 있을까요","wordCount":15},"emotion":[],"intent":[]},"answer":{"raw":{"text":"아 배달의 민족에서 가장 아쉬웠던 부분은 역시 배달료 일 것 같습니다. 어 배달료가 너무 비싸서 그 음식 요즘 물가도 많이 올라서 음식값도 비싼데 거기에 배달료까지 더하면 어 거기에 저희가 고객이 부담해야 되는 어 경제적 것이 너무 커 커서요. 어 그게 조금 어 아 조금 더 저렴해졌으면 좋겠습니다. 그러나 뭐 요즘 그 배달로 생계를 꾸려 가시는 분들도 굉장히 많기 때문에 어 그분들의 입장을 생각하면 어 너무 뭐 싼 값에 이용할 수는 없겠지요. 아 저희가 한 가지 어 어 힘든 점이 있다면 음 배달하시는 민 배달이 하 하시는 분들보다 배달의 민족이라는 회사에서 취하는 이익이 더 크지 않을까 이런 생각이 듭니다. 그래서 그 그런 그 기업을 운영하시는 분이 어 사회에 봉헌한다는 생각을 가지고 어 본인들의 이익금을 좀 줄여서 배달하시는 분이나 아니면 그 소상공인들 그 어 음식점을 하시는 분들한테 조금이라도 이익이 돌아갈 수 있도록 어 그런 배려와 그런 어 마인드를 가지고 경영을 해 주셨으면은 너무 감사할 것 같습니다. 어 저는 그래서 잘 이용하지는 않습니다.","wordCount":150},"emotion":[{"text":"아 배달의 민족에서 가장 아쉬웠던 부분은 역시 배달료 일 것 같습니다.","expression":"n-distress","category":"negative"}],"intent":[{"text":"","expression":"","category":"attitude"}],"summary":{"text":"배달의 민족은 음식값에 배달료까지 더하면 고객이 부담해야 되는 경제적 부담이 커 아쉽습니다. 그러나 배달로 생계를 꾸려 가시는 분들을 생각하면 너무 싼 값에 이용할 수는 없습니다. 배달 민족이라는 회사에서 취하는 이익이 더 커 배달하시는 분이나 소상공인들한테 조금이라도 이익이 돌아가도록 경영을 해 주셨으면 좋겠습니다.","wordCount":42}}},"rawDataInfo":{"question":{"fileFormat":"wav","fileSize":610318,"duration":19070,"samplingBit":16,"channelCount":1,"samplingRate":"16kHz","audioPath":"/Mock/01.Management/Female/New/ckmk_q_bm_f_n_199597.wav"},"answer":{"fileFormat":"wav","fileSize":2908238,"duration":90880,"samplingBit":16,"channelCount":1,"samplingRate":"16kHz","audioPath":"/Mock/01.Management/Female/New/ckmk_a_bm_f_n_199597.wav"}}}