{"version":"1.0","dataSet":{"info":{"date":"20230116","occupation":"BM","channel":"MOCK","place":"ONLINE","gender":"MALE","ageRange":"55-","experience":"NEW"},"question":{"raw":{"text":"배달의 민족을 사용하면서 서비스에서 아쉬움을 느꼈던 부분이 있으셨나요 있었다면 무엇인지 말씀해 주시기 바랍니다","wordCount":13},"emotion":[],"intent":[]},"answer":{"raw":{"text":"음식 배달하는데 저는 배달의민족과 쿠팡이츠를 이용을 합니다. 제가 주로 배달의민족을 쿠팡보다는 많이 이용하는 부분이 여기는 가격이 좀 쌉니다. 배달하는데 라이더에 가격이 쿠팡보다는 약 이천 원 정도가 평균적으로 싼 것 같더라고요. 그래서 배달의 민족을 이용을 하는데 싼 싸서 좋긴 한데 단점도 있습니다. 그것은 배달이 좀 늦더라고요. 그래서 배달 수수료가 쿠팡보다 싼 게 아닌가 싶은 생각도 듭니다. 그러다 보니깐 이 배달이 늦음으로써 음식에 음식이 식어서 맛이 없어지는 그런 부분도 있더라구요. 그래서 가끔은 제가 쿠팡 이츠를 이용해서 돈을 더 내더래도 빨리 그 음식을 배달을 받아서 먹는 경우도 있지만 대부분은 금전적인 걸 생각해서 배달의 민족을 에서 음식을 주문해서 쫌 싼 가격에 음식을 배달시켜 먹기도 합니다.","wordCount":101},"emotion":[],"intent":[{"text":"","expression":"","category":"attitude"}],"summary":{"text":"음식배달의 민족과 쿠팡이츠 중 배달의민족을 주로 이용합니다. 라이더에 가격이 좀 싼 편이지만 배달이 좀 늦으면 음식의 식어가 맛이 없어지는 단점이 있습니다. 대부분 금전적인 걸 생각해서 배달의 민족을 이용, 좀 싼 가격에 음식을 배달시키기도 합니다.","wordCount":34}}},"rawDataInfo":{"question":{"fileFormat":"wav","fileSize":349198,"duration":10910,"samplingBit":16,"channelCount":1,"samplingRate":"16kHz","audioPath":"/Mock/01.Management/Male/New/ckmk_q_bm_m_n_336155.wav"},"answer":{"fileFormat":"wav","fileSize":2758478,"duration":86200,"samplingBit":16,"channelCount":1,"samplingRate":"16kHz","audioPath":"/Mock/01.Management/Male/New/ckmk_a_bm_m_n_336155.wav"}}}