{"version":"1.0","dataSet":{"info":{"date":"20230116","occupation":"BM","channel":"MOCK","place":"ONLINE","gender":"MALE","ageRange":"55-","experience":"NEW"},"question":{"raw":{"text":"지금까지 살아오시면서 가장 힘들었던 경험은 무엇이었나요 그것을 어떻게 극복하셨는지도 말씀해 주세요","wordCount":11},"emotion":[],"intent":[]},"answer":{"raw":{"text":"지금까지 살아오면서 힘들었던 경험들은 꽤 있었습니다. 그중에서 기억나는 한 가지 말씀을 드리면은 일을 하면서 제 윗상사하고 서로 맞지 않아 가지고 굉장히 불화가 심했던 적이 있었습니다. 왜 그런지는 모르겠지마는 사사건건 제가 일을 하는 거에 대해서 상사 분께서 잔소리가 심하고 잘못을 질책하고 그리고 보고서 같은 경우에는 여러 차례 다시 작성하고 굉장히 힘들었습니다. 한 일 년 정도를 힘들게 버텼는데 정말 더 이상 버티기가 힘들 만큼 견디기가 어렸었는데 그래도 참았습니다. 그랬더니 얼마 안 있다가 이 상사 분께서 회사에 누를 끼쳐서 퇴직을 한 적이 있었습니다. 자연스럽게 새로운 분이 오셔 가지고 지금은 문제가 없었는데 돌이켜 보니까 제가 극복할 수 있었던 힘은 시간이었습니다. 참고 견디니깐 극복이 자연스럽게 된 것입니다.","wordCount":102},"emotion":[],"intent":[{"text":"","expression":"","category":"attitude"}],"summary":{"text":"지금까지 살아오면서 힘들었던 경험들은 꽤 있습니다. 일을 하면서 윗상사하고 서로 맞지 않아 가지고 굉장히 불화가 심했던 적이 있었는데 참았습니다. 그랬더니 얼마 안 있다가 상사분이 회사에 누를 끼쳐서 퇴직을 한 적이 있었습니다. 참고 견디다보니 극복이 자연스럽게 되었습니다.","wordCount":36}}},"rawDataInfo":{"question":{"fileFormat":"wav","fileSize":346958,"duration":10840,"samplingBit":16,"channelCount":1,"samplingRate":"16kHz","audioPath":"/Mock/01.Management/Male/New/ckmk_q_bm_m_n_341013.wav"},"answer":{"fileFormat":"wav","fileSize":2682638,"duration":83830,"samplingBit":16,"channelCount":1,"samplingRate":"16kHz","audioPath":"/Mock/01.Management/Male/New/ckmk_a_bm_m_n_341013.wav"}}}