{"version":"1.0","dataSet":{"info":{"date":"20230116","occupation":"BM","channel":"MOCK","place":"ONLINE","gender":"FEMALE","ageRange":"-34","experience":"NEW"},"question":{"raw":{"text":"직무를 수행하다가 난관에 봉착하는 경우도 발생할 수 있는데요 이럴 때 지원자님은 어떻게 해결을 하실 것 같은지 지원자님만의 해결법과 그 이유에 대해서도 함께 말씀해 주시기 바랍니다","wordCount":25},"emotion":[],"intent":[]},"answer":{"raw":{"text":"직무를 수행할 때 어 난관에 봉착하는 이유는 여러 가지가 있을 텐데요. 어 첫 번째로 제가 생각하는 난관에 봉착하는 이유는 해당 지식이 없기 때문에 라고 생각이 듭니다. 이런 부분은 제가 업무 매뉴얼이나 어 관련 서적 그리고 강의를 통해서 스스로 공부를 하면서 깨우친다면 얼마든지 해결을 할 수 있다고 생각을 합니다. 두 번째 난관에 봉착하는 이유는 어 그 업무에 대한 경험이 없기 때문입니다. 그렇기 때문에 이 부분은 어 제가 그 난관에 봉착하는 그런 횟수가 많아지고 빈도가 많아지면 많아질수록 해결해 나가는 속도나 그런 노하우들이 발전을 할 것이라고 생각을 하고 이 과정에서 해당 직무에 오랜 기간 근무하신 선배님들을 찾아가서 어 조언을 구하거나 어 말씀을 아 대화를 나누는 등의 그런 방법으로 해결해 나갈 수 있을 것 같습니다. 어 이런 직무 수행시 난관에 봉착하는 두 가지 이유 이유를 어 저는 잘 헤쳐 나갈 수 있는 그런 능력이 된다고 생각하고 어 열심히 노력해서 점점 더 발전되는 모습을 보여드릴 수 있습니다.","wordCount":142},"emotion":[],"intent":[{"text":"","expression":"","category":"attitude"}],"summary":{"text":"직무 수행 시 난관에 봉착하는 두 가지 이유는 해당 지식이 없기 때문이고, 업무 경험이 없기 때문입니다. 빈도가 많아질수록 해결해 나가는 속도나 노하우들이 발전을 할 것이라고 생각을 하고 해당 직무에 오랜 기간 근무하신 선배님들을 찾아가 조언을 구하는 등의 방법으로 해결해 나갈 수 있을 것 같습니다.","wordCount":44}}},"rawDataInfo":{"question":{"fileFormat":"wav","fileSize":464718,"duration":14520,"samplingBit":16,"channelCount":1,"samplingRate":"16kHz","audioPath":"/Mock/01.Management/Female/New/ckmk_q_bm_f_n_308805.wav"},"answer":{"fileFormat":"wav","fileSize":3055438,"duration":95480,"samplingBit":16,"channelCount":1,"samplingRate":"16kHz","audioPath":"/Mock/01.Management/Female/New/ckmk_a_bm_f_n_308805.wav"}}}