{"version":"1.0","dataSet":{"info":{"date":"20230116","occupation":"BM","channel":"MOCK","place":"ONLINE","gender":"MALE","ageRange":"-34","experience":"NEW"},"question":{"raw":{"text":"면접자님께서는 팀으로 일하는 것과 혼자 일하는 것 중 어느 것을 더 선호하시는지 선호하시는 이유와 함께 말씀해 주세요","wordCount":17},"emotion":[],"intent":[]},"answer":{"raw":{"text":"저는 팀으로 일하는 것과 혼자 일하는 것 중에 팀으로 일하는 것을 더 선호합니다. 원래 저는 혼자 일하는 것을 더 선호했습니다. 일하는 모든 과정에 제가 관여하고 제가 처음부터 끝까지 제 마음대로 하는 것이 마음이 편했기 때문입니다. 그래서 저는 제가 혼자 일하는 것이 잘 맞고 혼자 일한 결과물이 더 좋다고 생각했습니다. 하지만 한 공모전을 하면서 제 이런 생각이 바뀌게 되었는데요. 당시 공모전에선 반드시 조를 만들어서 그 조별로 과제를 수행해야 했습니다. 저는 그곳에서 세 명의 조원들과 함께 프로젝트를 진행했습니다. 이 프로젝트를 진행하면서 처음에는 제가 원래 하던 대로 전반적인 분야에 제 원하는 의도대로 일을 진행하고자 했습니다. 하지만 일을 하면서 상대방이 더 잘하는 부분이 있다는 것을 깨닫게 되었고 또 제가 미처 생각하지 못한 부분들을 팀원들이 이야기를 하고 아이디어를 제시하는 모습을 보면서 아 내가 혼자 생각하는 것보다 이렇게 팀으로 했을 때 더 창의적인 결과물이 나올 수 있겠다는 생각을 했습니다. 그리고 그때 그 공모전에서 정말 좋은 결과를 얻게 되었는데요. 바로 전체 일 등인 최우수상을 거머줬습니다. 그때부터 저는 혼자 일하는 것보다 팀으로 일하는 것이 더 좋은 성과를 낼 수 있다는 것을 깨닫게 되었습니다.","wordCount":165},"emotion":[],"intent":[{"text":"","expression":"","category":"attitude"}],"summary":{"text":"업무 과정의 모든 과정을 제 마음대로 하는 것이 마음이 편했기 때문에 혼자 일하는 것을 더 선호했지만, 한 공모전에서 전체 일 등인 최우수상을 거머쥔 이후로는 혼자 일하는 것보다 팀으로 일하는 것이 더 좋은 성과를 낼 수 있다는 것을 깨닫게 되었습니다.","wordCount":39}}},"rawDataInfo":{"question":{"fileFormat":"wav","fileSize":333518,"duration":10420,"samplingBit":16,"channelCount":1,"samplingRate":"16kHz","audioPath":"/Mock/01.Management/Male/New/ckmk_q_bm_m_n_279423.wav"},"answer":{"fileFormat":"wav","fileSize":3737358,"duration":116790,"samplingBit":16,"channelCount":1,"samplingRate":"16kHz","audioPath":"/Mock/01.Management/Male/New/ckmk_a_bm_m_n_279423.wav"}}}