{"version":"1.0","dataSet":{"info":{"date":"20230116","occupation":"BM","channel":"MOCK","place":"ONLINE","gender":"FEMALE","ageRange":"-34","experience":"NEW"},"question":{"raw":{"text":"지원자님의 전공과 관련해서 최근 부족하다고 느끼고 따로 공부를 하고 있는 분야가 있습니까","wordCount":12},"emotion":[],"intent":[]},"answer":{"raw":{"text":"저의 전공과 관련해서 어 저는 음 이런 돈의 흐름과 관리에 대해서 조금 더 부족하다고 느껴서 이 관련된 공부를 하고 있습니다. 바로 재무 회계에 관련된 공부인데요. 이런 공부를 통해서 제가 해 나가는 그런 일적인 부분에서 어떻게 돈을 활용하고 또 이 돈의 흐름은 어떻게 회사로 이익과 연결이 되는가에 대해서 관련지어서 공부를 하고 있습니다. 저의 전공은 경영인데요 이 경영에 있어서 정말 중요한 것이 돈을 파악하고 돈을 관리하는 것입니다. 어찌됐든 기업의 궁극적인 목표는 어 이익이기 때문에 그런 금전적 이익에 관련해서 좀 혜안을 가지고 있는 사람이 결국에는 어 길게 이 회사에 도움이 되는 사람이 될 것이라는 생각을 합니다. 그래서 공부를 하게 되었고 실제로 이 공부를 통해서 제가 하는 사업에 대해서 예산을 짜거나 아니면 집행을 할 때 조금 더 신중하고 앞에 일어날 상황에 대비를 하는 등의 그런 어 차이점을 볼 수 있었습니다 스스로. 그래서 앞으로도 이런 공부를 지속적으로 해 나갈 생각입니다.","wordCount":135},"emotion":[],"intent":[{"text":"","expression":"","category":"attitude"}],"summary":{"text":"경영에 있어서 돈을 파악하고 돈을 관리하는 것이 정말 중요하기 때문에 금전적 이익에 관련해서 좀 혜안을 가지고 있는 사람이 결국에는 회사에 도움이 되는 사람이 될 것이라는 생각을 합니다. 따라서 이런 공부를 지속적으로 해 나갈 계획입니다.","wordCount":34}}},"rawDataInfo":{"question":{"fileFormat":"wav","fileSize":294478,"duration":9200,"samplingBit":16,"channelCount":1,"samplingRate":"16kHz","audioPath":"/Mock/01.Management/Female/New/ckmk_q_bm_f_n_350904.wav"},"answer":{"fileFormat":"wav","fileSize":3006798,"duration":93960,"samplingBit":16,"channelCount":1,"samplingRate":"16kHz","audioPath":"/Mock/01.Management/Female/New/ckmk_a_bm_f_n_350904.wav"}}}