{"version":"1.0","dataSet":{"info":{"date":"20230116","occupation":"BM","channel":"MOCK","place":"ONLINE","gender":"FEMALE","ageRange":"35-44","experience":"NEW"},"question":{"raw":{"text":"이전 직장을 그만두신 특별한 이유가 있나요 그리고 현 직장도 같은 이유로 그만두시지는 않을까요","wordCount":13},"emotion":[],"intent":[]},"answer":{"raw":{"text":"어 이전에 제가 영어 학원에서 일을 하게 되었는데 어 그 당시에 제가 일을 하면서 어 제가 가르치는 기술이 부족하다고 느꼈습니다. 그리고 학생을 어 대하는 것도 학생을 지도하는 것도 제가 어려움을 느꼈고 한계를 느꼈기 때문에 제가 대학원에 진학을 하기 위해서 직장을 그만두게 되었습니다. 어 학원은 저녁 늦게까지 하는데 음 시간이 겹치고 또 그것들을 어 두 가지를 한꺼번에 할 수 없기 때문에 음 원장님께 이야기해서 충분히 이유를 설명했을 때 어 원장님께서도 흔쾌히 잘 받아들여 주셔서 그것들을 좋은 마음으로 어 인사를 하고 또 선생님이 필요하다면 나중에도 서로가 도울 수 있는 관계가 되자고 그때 이야기를 하고 좋은 관계로 나오게 되었습니다. 그리고 나중에 제가 필요한 것들을 뭐 필요한 것들을 어 서로가 요청할 수 있는 그런 관계가 가지게 되었고 또 제가 어 그곳에서 많은 것을 배우고 나와서 감사한 마음을 가지고 어 선생님께 인사를 하고 나왔습니다. 그래서 그 후에 어 대학원을 진학을 하게 되었고 또 어 기회가 좋아서 학교에서 일을 하게 되었습니다. 그래서 제가 어 제가 배울 어 제 한계를 깨닫고 배울 수 있는 기회를 어 삼게 되어서 어 직장을 그만둔 것에 대해서 후회하지 않고 제가 그것들을 꼭 필요한 과정이었다고 생각합니다. 그런데 지금은 어 일과 같이 병행을 하기 때문에 그만둘 가능성은 없다고 생각합니다.","wordCount":186},"emotion":[],"intent":[{"text":"","expression":"","category":"attitude"}],"summary":{"text":"이전에 영어 학원에서 일을 하며 가르치는 기술이 부족하고 학생을 대하는 것과 학생을 지도하는 것도 어려움을 느껴 직장을 그만두었습니다. 학원은 늦게까지 하는데 시간이 겹치고 둘을 한꺼번에 할 수 없어서 원장님께 이야기해서 좋은 관계로 나왔습니다. 그후 대학원을 진학하고 학교에서 일을 하게 되었는데 그때 직장을 그만둔 것에 대해서 후회하지 않고 꼭 필요한 과정이었다고 생각합니다.","wordCount":51}}},"rawDataInfo":{"question":{"fileFormat":"wav","fileSize":243278,"duration":7600,"samplingBit":16,"channelCount":1,"samplingRate":"16kHz","audioPath":"/Mock/01.Management/Female/New/ckmk_q_bm_f_n_350427.wav"},"answer":{"fileFormat":"wav","fileSize":3754958,"duration":117340,"samplingBit":16,"channelCount":1,"samplingRate":"16kHz","audioPath":"/Mock/01.Management/Female/New/ckmk_a_bm_f_n_350427.wav"}}}