{"version":"1.0","dataSet":{"info":{"date":"20230116","occupation":"BM","channel":"MOCK","place":"ONLINE","gender":"MALE","ageRange":"-34","experience":"NEW"},"question":{"raw":{"text":"면접자님의 전공과 관련해서 최근 부족하다고 느끼고 따로 공부를 하고 있는 분야가 있는지 저희에게 설명 부탁드리겠습니다","wordCount":15},"emotion":[],"intent":[]},"answer":{"raw":{"text":"제 전공은 신소재 공학으로 과학과 관련된 전공입니다. 하지만 이제 모든 회사들의 흥망성쇠는 경제적인 흐름과 사회적인 이슈에 따라서 결정이 된다고 생각을 하기 때문에 그 부분이 양이 부족하다고 느껴서 현재는 경제 흐름에 관련된 공부를 하고 있습니다. 사회적인 이슈를 공부를 하기에는 아직 어 그 정도의 이해도가 딸리 부족해서 경제적인 흐름을 먼저 공부를 해 보고 있습니다.","wordCount":52},"emotion":[{"text":"제 전공은 신소재 공학으로 과학과 관련된 전공입니다.","expression":"u-fact","category":"neutral"}],"intent":[{"text":"제 전공은 신소재 공학으로 과학과 관련된 전공입니다.","expression":"c_private","category":"background"}],"summary":{"text":"신소재 공학에 과학과 관련된 전공이지만 회사들의 흥망성쇠는 경제적인 흐름과 사회적인 이슈에 따라 결정된다고 생각하여 경제적인 흐름을 먼저 공부해 보고 있습니다.","wordCount":20}}},"rawDataInfo":{"question":{"fileFormat":"wav","fileSize":312398,"duration":9760,"samplingBit":16,"channelCount":1,"samplingRate":"16kHz","audioPath":"/Mock/01.Management/Male/New/ckmk_q_bm_m_n_384919.wav"},"answer":{"fileFormat":"wav","fileSize":1053518,"duration":32920,"samplingBit":16,"channelCount":1,"samplingRate":"16kHz","audioPath":"/Mock/01.Management/Male/New/ckmk_a_bm_m_n_384919.wav"}}}