{"version":"1.0","dataSet":{"info":{"date":"20230116","occupation":"BM","channel":"MOCK","place":"ONLINE","gender":"MALE","ageRange":"-34","experience":"NEW"},"question":{"raw":{"text":"커뮤니케이션을 잘 할 수 있는 본인만의 스킬이 있다면 지금 이 자리에서 한번 저희에게 보여주시면 좋겠습니다","wordCount":15},"emotion":[],"intent":[]},"answer":{"raw":{"text":"저는 주변에서 소통을 잘하기로 정평이 나 있습니다. 친구들과 지인들은 저와 이야기를 나누면 마음이 너무나 편해지고 또 즐겁다고 얘기하곤 하는데요. 저는 사람들과 잘 커뮤니케이션을 이어가기 위해서 이 공통 분모를 최대한 많이 만들고자 노력합니다. 그래서 제가 먼저 이야기를 시작하기보단 상대방의 이야기를 듣고 그 이후에 해당 사람이 어떠한 분야에 관심이 있는지를 파악하고 그것과 관련된 이야기를 주로 진행하곤 합니다. 제가 이럴 수 있는 이유는 제가 좋아하는 분야가 굉장히 다방면에 걸쳐 있기 때문인데요. 그래서 상대방이 관심 있는 분야에 대해 먼저 들어보고 해당 분야에 제가 갖고 있는 생각과 지식을 나누는 행위를 통해서 이야기를 매끄럽게 이끌어 갈 수 있다고 생각합니다. 예를 들어서 상대방과 이야기를 할 때 제가 먼저 무엇을 좋아한다고 말하기보단 혹시 평소에 시간 날 때 뭘 많이 하시나요. 이런 식으로 평소에 자신의 취미가 무엇인지 물어보곤 합니다. 그리고 상대방이 그것에 대해 답변을 하면 저는 이런 식으로 저의 반응을 보입니다. 오 저도 그거 하는 거 되게 좋아하는데 혹시 언제부터 시작하셨어요. 왜 좋아하시게 되신 거죠. 이런 식으로 이야기를 진행합니다. 그러면 상대방은 신나서 자신의 이야기를 계속 하게 되는데요. 이러한 방식을 토대로 저는 커뮤니케이션을 이어갑니다.","wordCount":164},"emotion":[],"intent":[{"text":"","expression":"","category":"attitude"}],"summary":{"text":"저는 사람들과 잘 커뮤니케이션을 이어가기 위해 먼저 이야기를 시작하기보다 상대방의 이야기를 듣고 그 이후에 해당 사람이 어떠한 분야에 관심이 있는지를 파악하고 그것과 관련된 이야기를 주로 진행하곤 합니다. 제가 좋아하는 분야가 굉장히 다방면에 걸쳐 있기 때문인데, 상대방이 관심 있는 분야에 대해 먼저 들어보고 그 분야에 제가 갖고 있는 생각과 지식을 나누는 행위를 통해서 이야기를 매끄럽게 이끌어 갈 수 있다고 생각합니다.","wordCount":59}}},"rawDataInfo":{"question":{"fileFormat":"wav","fileSize":310478,"duration":9700,"samplingBit":16,"channelCount":1,"samplingRate":"16kHz","audioPath":"/Mock/01.Management/Male/New/ckmk_q_bm_m_n_272655.wav"},"answer":{"fileFormat":"wav","fileSize":3793678,"duration":118550,"samplingBit":16,"channelCount":1,"samplingRate":"16kHz","audioPath":"/Mock/01.Management/Male/New/ckmk_a_bm_m_n_272655.wav"}}}