{"version":"1.0","dataSet":{"info":{"date":"20230116","occupation":"BM","channel":"MOCK","place":"ONLINE","gender":"FEMALE","ageRange":"-34","experience":"NEW"},"question":{"raw":{"text":"이전 직장을 그만두셨던 특별한 이유가 있나요 또한 현재 직장도 같은 이유로 그만둘 가능성이 있다고 생각하시나요","wordCount":15},"emotion":[],"intent":[]},"answer":{"raw":{"text":"이전 직장을 그만둔 이유는 개인적으로 저의 경력에 발전에 어 아주 큰 도움이 되진 않는다고 생각했었고 하지만 모든 일은 음 도움이 안 되는 건 없다 라고는 생각을 합니다. 다만 어 조금 더 인생을 좀 길게 봤을 때는 그렇게 생각을 하였구요. 이전 직장 역시 저한테 어쨌든 결과론적으로는 도움이 됐고 또 현 직장 같은 경우에는 제가 좀 어 마지막이라고 생각을 해서 온 것도 있고 또 제가 나이를가 들수록 사실은 어 뭔가 어떤 분야를 좀 깊이 해야겠다 라는 생각을 계속 하고 있기 때문에 어 이전 직장처럼 그냥 쉽게 관두기에는 뭐 그 선택과 집중을 했던 그 과정이 정말 더 힘들었기 때문에 사실 다시는 하고 싶지도 않고 또 같은 이유로 그만두고 싶은 생각도 사실 잘 없습니다. 네 제 이유입니다.","wordCount":113},"emotion":[],"intent":[{"text":"","expression":"","category":"attitude"}],"summary":{"text":"이전 직장이 제 경력에 큰 도움이 되지 않는다고 생각했고, 현 직장은 마지막이라고 생각하고 있고, 선택과 집중을 했던 그 과정이 정말 더 힘들었기 때문에 다시 그만두고 싶은 생각은 없습니다.","wordCount":28}}},"rawDataInfo":{"question":{"fileFormat":"wav","fileSize":622798,"duration":19460,"samplingBit":16,"channelCount":1,"samplingRate":"16kHz","audioPath":"/Mock/01.Management/Female/New/ckmk_q_bm_f_n_277826.wav"},"answer":{"fileFormat":"wav","fileSize":2614798,"duration":81710,"samplingBit":16,"channelCount":1,"samplingRate":"16kHz","audioPath":"/Mock/01.Management/Female/New/ckmk_a_bm_f_n_277826.wav"}}}