{"version":"1.0","dataSet":{"info":{"date":"20230116","occupation":"BM","channel":"MOCK","place":"ONLINE","gender":"MALE","ageRange":"35-44","experience":"NEW"},"question":{"raw":{"text":"이제까지 속해 있었던 조직이나 단체 속에서 본인이 주로 어떤 역할을 하는 사람이었는지 말씀해 주세요","wordCount":14},"emotion":[],"intent":[]},"answer":{"raw":{"text":"그동안 저는 제가 속한 조직에서 원하는 목표를 달성하기 위해서 팀을 이끄는 팀 리더 자리에 있었습니다. 제가 주도한 팀은 좋은 결과를 얻을 수 있었고 모두 좋은 협업으로 구성원 모두가 좋은 분위기 속에서 즐겁게 일을 할 수 있었습니다. 그것은 모두 제 덕입니다. 제가 잘나고 똑똑하기 때문에 그들을 좋은 분위기 하에서 일을 할 수 있어 일을 할 수 있게 관리할 수 있었고 또한 제가 잘나고 독특하기 때문에 좋은 결과를 도출해서 끌어낼 수 있었습니다. 그러니까 저를 뽑아 주십시오.","wordCount":74},"emotion":[{"text":"제가 주도한 팀은 좋은 결과를 얻을 수 있었고 모두 좋은 협업으로 구성원 모두가 좋은 분위기 속에서 즐겁게 일을 할 수 있었습니다.","expression":"p-happiness","category":"positive"}],"intent":[{"text":"","expression":"","category":"attitude"}],"summary":{"text":"제가 속한 조직은 좋은 결과를 얻을 수 있었고 모두 좋은 협업으로 좋은 분위기 속에서 즐겁게 일을 할 수 있었습니다. 그것은 모두 제 덕이니 저를 뽑아 주십시오.","wordCount":26}}},"rawDataInfo":{"question":{"fileFormat":"wav","fileSize":266318,"duration":8320,"samplingBit":16,"channelCount":1,"samplingRate":"16kHz","audioPath":"/Mock/01.Management/Male/New/ckmk_q_bm_m_n_263932.wav"},"answer":{"fileFormat":"wav","fileSize":1355918,"duration":42370,"samplingBit":16,"channelCount":1,"samplingRate":"16kHz","audioPath":"/Mock/01.Management/Male/New/ckmk_a_bm_m_n_263932.wav"}}}