{"version":"1.0","dataSet":{"info":{"date":"20230116","occupation":"BM","channel":"MOCK","place":"ONLINE","gender":"FEMALE","ageRange":"45-54","experience":"NEW"},"question":{"raw":{"text":"시간이 남을 때 무슨 일을 하시나요 그 일을 하는 이유에 대해서도 구체적으로 설명해 주신다면 더욱 좋을 것 같습니다","wordCount":18},"emotion":[],"intent":[]},"answer":{"raw":{"text":"저는 시간이 남을 때 주로 바느질을 합니다. 바느질을 하는 이유는 인형을 만들기 위해서인데요. 인형을 만들어서 저는 저희 아이에게 주고 다른 데 기부도 합니다. 제가 바느질을 하게 된 이유는 최근에 어 봉사 활동을 갈 일이 있었는데요. 그곳에서 아이들에게 양말 인형을 만들어 주더라구요 손수 바느질을 해서. 저는 양말이 인형으로 변하는 과정이 굉장히 신기했는데 아이들은 그것을 받아보고 무척 좋아했습니다. 시설에 있는 친구들 같은 경우에는 애착 형성이 부족한 부분이 있을 수 있다고 해요. 그래서 애착 인형을 만들어주는 거라고 들었습니다. 그렇게 이야기를 듣고 집에 와서 저도 잘 안 신는 양말로 인형을 만들어서 아이들에게 주었는데요. 굉장히 좋아하더라구요. 그래서 그때부터 저는 시간이 날 때마다 바느질을 통해 양말 인형을 만들고 저희 아이들에게 주기도 하지만 이렇게 시설에 있는 친구들에게 애착 인형 인형으로 기부를 하고 있습니다.","wordCount":116},"emotion":[],"intent":[{"text":"","expression":"","category":"attitude"}],"summary":{"text":"제가 바느질을 하는 이유는 인형을 만들기 위해서 인데, 최근 봉사 활동을 가면서 아이들이 인형으로 변하는 과정을 보고 무척 좋아하였습니다. 시설에 있는 친구들의 애착 형성을 위해 인형을 만들어주는 것이라고 들었습니다. 그래서 제가 시간이 날 때마다 인형을 만들고 다른 데 기부를 하고 있습니다.","wordCount":41}}},"rawDataInfo":{"question":{"fileFormat":"wav","fileSize":620238,"duration":19380,"samplingBit":16,"channelCount":1,"samplingRate":"16kHz","audioPath":"/Mock/01.Management/Female/New/ckmk_q_bm_f_n_318488.wav"},"answer":{"fileFormat":"wav","fileSize":2479118,"duration":77470,"samplingBit":16,"channelCount":1,"samplingRate":"16kHz","audioPath":"/Mock/01.Management/Female/New/ckmk_a_bm_f_n_318488.wav"}}}