{"version":"1.0","dataSet":{"info":{"date":"20230116","occupation":"BM","channel":"MOCK","place":"ONLINE","gender":"MALE","ageRange":"35-44","experience":"NEW"},"question":{"raw":{"text":"오늘 이 면접 준비하시느라 굉장히 고생이 많으셨을 텐데요 만약에 지원자님께서 열심히 준비하셨겠지만 최종 탈락하시게 된다면 어떤 점이 부족해서 탈락했을 거라고 예상을 하실 것 같나요","wordCount":24},"emotion":[],"intent":[]},"answer":{"raw":{"text":"그것은 아마 제가 용모를 단정히 하지 않아서 떨어졌다고 생각할 것입니다. 왜냐하면 저는 그동안 다른 일을 한다고 일이 너무 바빠서 이발과 그다음에 옷차림새에 신경을 쓸 겨를이 없었습니다. 그렇기 때문에 이렇게 수염이 덥수룩하고 머리도 제대로 손질되지 않은 채로 이 면접에 임할 수 밖에 없었습니다. 그리고 오는 길에 교통사고가 나서 이렇게 찢어지고 해진 옷을 입을 고 올 수 밖에 없었습니다. 면접에 늦지 않기 위하여 최대한 헐레벌떡 뛰어오다 보니 옷을 제대로 정리할 수도 없었습니다. 그렇기 때문에 제가 면접에서 떨어진다면 이렇게 지저분한 복장과 용무 때문에 떨어졌을 것이라고 생각하겠습니다.","wordCount":83},"emotion":[],"intent":[{"text":"","expression":"","category":"attitude"}],"summary":{"text":"저는 다른 일을 한다고 일이 바빠서 이발과 옷차림새에 신경 쓸 겨를이 없어 수염이 덥수룩하고 머리도 제대로 손질되지 않은 채로 면접에 임했습니다. 게다가 교통사고가 나서 찢어진 옷을 입고 왔기에 옷 정리를 할 수 없었습니다.","wordCount":33}}},"rawDataInfo":{"question":{"fileFormat":"wav","fileSize":521038,"duration":16280,"samplingBit":16,"channelCount":1,"samplingRate":"16kHz","audioPath":"/Mock/01.Management/Male/New/ckmk_q_bm_m_n_316748.wav"},"answer":{"fileFormat":"wav","fileSize":1514958,"duration":47340,"samplingBit":16,"channelCount":1,"samplingRate":"16kHz","audioPath":"/Mock/01.Management/Male/New/ckmk_a_bm_m_n_316748.wav"}}}